msdnicrosoft_logger/__init__.py
msdnicrosoft_logger-0.0.8.dist-info/LICENSE
msdnicrosoft_logger-0.0.8.dist-info/METADATA
msdnicrosoft_logger-0.0.8.dist-info/WHEEL
msdnicrosoft_logger-0.0.8.dist-info/top_level.txt
msdnicrosoft_logger-0.0.8.dist-info/RECORD
