Metadata-Version: 2.1
Name: msdnicrosoft-logger
Version: 0.0.8
Summary: 自己手写的 logger
Home-page: https://github.com/MSDNicrosoft/logger
Author: MSDNicrosoft
Author-email: wang3311835119@hotmail.com
License: MIT
Platform: UNKNOWN
Classifier: License :: OSI Approved :: MIT License
Classifier: Programming Language :: Python
Classifier: Programming Language :: Python :: 3
Classifier: Operating System :: OS Independent
Requires-Python: >=3.6.0
License-File: LICENSE
Requires-Dist: colorama (>=0.4.4)
